operacionesvicky/__init__.py
operacionesvicky/modulo.py
operacionesvicky-0.1.0.dist-info/METADATA
operacionesvicky-0.1.0.dist-info/WHEEL
operacionesvicky-0.1.0.dist-info/top_level.txt
operacionesvicky-0.1.0.dist-info/RECORD
